NpdFsData/__init__.py
npd_fs_data-0.0.4.dist-info/METADATA
npd_fs_data-0.0.4.dist-info/WHEEL
npd_fs_data-0.0.4.dist-info/top_level.txt
npd_fs_data-0.0.4.dist-info/RECORD
