Metadata-Version: 2.1
Name: npd-fs-data
Version: 0.0.4
Summary: Library for easy programatic access Financial Services info
Home-page: https://NPDGroup@dev.azure.com/NPDGroup/NPDFinancialServices/_git/WhaleWisdom
Author: Max Leonard
Author-email: maxhleonard@gmail.com
Classifier: Programming Language :: Python :: 3
Classifier: License :: OSI Approved :: MIT License
Classifier: Operating System :: OS Independent
Requires-Python: >=3.6
Requires-Dist: azure-storage-blob
Requires-Dist: azure-data-tables
Requires-Dist: pandas
